[
  {
    "_id": "15c63b21-023f-f111-bec6-7c1e52873f9b",
    "cr9b2_jirakey": "PTH-162022",
    "cr9b2_jiraurl": "https://jira.cc.bmwgroup.net/browse/PTH-162022",
    "cr9b2_name": "L2_HV",
    "cr9b2_duedate": "24.03.2026 00:00",
    "cr9b2_ilevelnames": "[\"NA00-26-07-500\",\"NA05-26-07-500\",\"NA06-26-07-500\"]",
    "cr9b2_parentjiraissue": "PTH-162020",
    "cr9b2_parentbranches": "[\"PTH-06\"]",
    "cr9b2_brvs": "[]",
    "cr9b2_sops": "[]",
    "cr9b2_kw": "13",
    "cr9b2_year": "2.026",
    "cr9b2_yearweek": "2026-13"
  },
  {
    "_id": "1dc63b21-023f-f111-bec6-7c1e52873f9b",
    "cr9b2_jirakey": "PTH-165705",
    "cr9b2_jiraurl": "https://jira.cc.bmwgroup.net/browse/PTH-165705",
    "cr9b2_name": "L3_HV",
    "cr9b2_duedate": "24.02.2026 00:00",
    "cr9b2_ilevelnames": "[\"G065-26-11-450\",\"G065-27-03-410\",\"G065-27-07-360\",\"G065-27-11-320\",\"G065-28-03-280\",\"G065-28-07-230\",\"NA00-26-07-480\",\"NA00-26-11-450\",\"NA00-27-03-410\",\"NA00-27-07-360\",\"NA00-27-11-320\",\"NA00-28-03-280\",\"NA00-28-11-190\",\"NA00-29-03-150\",\"NA05-26-07-480\",\"NA05-26-11-450\",\"NA05-27-03-410\",\"NA05-27-07-360\",\"NA05-27-11-320\",\"NA05-28-11-190\",\"NA05-29-03-150\",\"NA06-26-07-480\",\"NA06-26-11-450\",\"NA06-27-03-410\",\"NA06-27-07-360\",\"NA06-28-03-280\",\"NA06-28-07-230\",\"RR45-27-07-360\"]",
    "cr9b2_parentjiraissue": "PTH-165702",
    "cr9b2_parentbranches": "[\"PTH-06\"]",
    "cr9b2_brvs": "[]",
    "cr9b2_sops": "[]",
    "cr9b2_kw": "9",
    "cr9b2_year": "2.026",
    "cr9b2_yearweek": "2026-09"
  },
  {
    "_id": "24c63b21-023f-f111-bec6-7c1e52873f9b",
    "cr9b2_jirakey": "PTH-168869",
    "cr9b2_jiraurl": "https://jira.cc.bmwgroup.net/browse/PTH-168869",
    "cr9b2_name": "L1_HV",
    "cr9b2_duedate": "12.02.2026 00:00",
    "cr9b2_ilevelnames": "[\"NA00-26-07-490\",\"NA05-26-07-490\",\"NA06-26-07-490\"]",
    "cr9b2_parentjiraissue": "PTH-168337",
    "cr9b2_parentbranches": "[\"PTH-06\"]",
    "cr9b2_brvs": "[]",
    "cr9b2_sops": "[]",
    "cr9b2_kw": "7",
    "cr9b2_year": "2.026",
    "cr9b2_yearweek": "2026-07"
  },
  {
    "_id": "1ec63b21-023f-f111-bec6-7c1e52873f9b",
    "cr9b2_jirakey": "PTH-165118",
    "cr9b2_jiraurl": "https://jira.cc.bmwgroup.net/browse/PTH-165118",
    "cr9b2_name": "L3_HV",
    "cr9b2_duedate": "24.02.2026 00:00",
    "cr9b2_ilevelnames": "[\"G065-26-07-480\",\"G065-26-11-450\",\"G065-27-03-410\",\"G065-27-07-360\",\"G065-27-11-320\",\"G065-28-03-280\",\"G065-28-07-230\",\"NA00-26-07-480\",\"NA00-26-11-450\",\"NA00-27-03-410\",\"NA00-27-07-360\",\"NA00-27-11-320\",\"NA00-28-03-280\",\"NA00-28-11-190\",\"NA00-29-03-150\",\"NA05-26-07-480\",\"NA05-26-11-450\",\"NA05-27-03-410\",\"NA05-27-07-360\",\"NA05-27-11-320\",\"NA05-28-11-190\",\"NA05-29-03-150\",\"NA06-26-07-480\",\"NA06-26-11-450\",\"NA06-27-03-410\",\"NA06-27-07-360\",\"NA06-28-03-280\",\"NA06-28-07-230\",\"RR45-27-07-360\"]",
    "cr9b2_parentjiraissue": "PTH-165114",
    "cr9b2_parentbranches": "[\"PTH-06\"]",
    "cr9b2_brvs": "[]",
    "cr9b2_sops": "[]",
    "cr9b2_kw": "9",
    "cr9b2_year": "2.026",
    "cr9b2_yearweek": "2026-09"
  },
  {
    "_id": "c5a5341e-023f-f111-bec6-0022489c460d",
    "cr9b2_jirakey": "PTH-162014",
    "cr9b2_jiraurl": "https://jira.cc.bmwgroup.net/browse/PTH-162014",
    "cr9b2_name": "L2_HV",
    "cr9b2_duedate": "24.02.2026 00:00",
    "cr9b2_ilevelnames": "[\"G065-27-03-419\"]",
    "cr9b2_parentjiraissue": "PTH-162012",
    "cr9b2_parentbranches": "[\"PTH-06\"]",
    "cr9b2_brvs": "[]",
    "cr9b2_sops": "[]",
    "cr9b2_kw": "9",
    "cr9b2_year": "2.026",
    "cr9b2_yearweek": "2026-09"
  },
  {
    "_id": "22044e20-023f-f111-bec6-7ced8d4a37b0",
    "cr9b2_jirakey": "PTH-178789",
    "cr9b2_jiraurl": "https://jira.cc.bmwgroup.net/browse/PTH-178789",
    "cr9b2_name": "L1",
    "cr9b2_duedate": "07.05.2026 00:00",
    "cr9b2_ilevelnames": "[\"G065-26-11-480\",\"G065-27-03-450\",\"G065-27-07-400\",\"G065-27-11-360\",\"G065-28-03-320\",\"G065-28-07-270\",\"G065-28-11-230\",\"NA00-26-11-480\",\"NA00-27-03-450\",\"NA00-27-07-400\",\"NA00-27-11-360\",\"NA00-28-03-320\",\"NA00-28-11-230\",\"NA00-29-03-190\",\"NA05-26-11-480\",\"NA05-27-03-450\",\"NA05-27-07-400\",\"NA05-27-11-360\",\"NA05-28-11-230\",\"NA05-29-03-190\",\"NA06-26-11-480\",\"NA06-27-03-450\",\"NA06-27-07-400\",\"NA06-27-11-360\",\"NA06-28-03-320\",\"NA06-28-07-270\",\"RR45-27-07-400\"]",
    "cr9b2_parentjiraissue": "PTH-170497",
    "cr9b2_parentbranches": "[\"PTH-06\"]",
    "cr9b2_brvs": "[]",
    "cr9b2_sops": "[]",
    "cr9b2_kw": "19",
    "cr9b2_year": "2.026",
    "cr9b2_yearweek": "2026-19"
  },
  {
    "_id": "18c63b21-023f-f111-bec6-7c1e52873f9b",
    "cr9b2_jirakey": "PTH-162414",
    "cr9b2_jiraurl": "https://jira.cc.bmwgroup.net/browse/PTH-162414",
    "cr9b2_name": "FB",
    "cr9b2_duedate": "10.03.2026 00:00",
    "cr9b2_ilevelnames": "[\"G065-26-11-459\",\"G065-27-03-419\",\"G065-27-07-369\"]",
    "cr9b2_parentjiraissue": "PTH-162412",
    "cr9b2_parentbranches": "[\"PTH-06\"]",
    "cr9b2_brvs": "[]",
    "cr9b2_sops": "[]",
    "cr9b2_kw": "11",
    "cr9b2_year": "2.026",
    "cr9b2_yearweek": "2026-11"
  },
  {
    "_id": "24044e20-023f-f111-bec6-7ced8d4a37b0",
    "cr9b2_jirakey": "PTH-180146",
    "cr9b2_jiraurl": "https://jira.cc.bmwgroup.net/browse/PTH-180146",
    "cr9b2_name": "FB",
    "cr9b2_duedate": "21.04.2026 00:00",
    "cr9b2_ilevelnames": "[\"NA00-26-07-510\",\"NA05-26-07-510\"]",
    "cr9b2_parentjiraissue": "PTH-180145",
    "cr9b2_parentbranches": "[\"PTH-06\"]",
    "cr9b2_brvs": "[]",
    "cr9b2_sops": "[]",
    "cr9b2_kw": "17",
    "cr9b2_year": "2.026",
    "cr9b2_yearweek": "2026-17"
  },
  {
    "_id": "23044e20-023f-f111-bec6-7ced8d4a37b0",
    "cr9b2_jirakey": "PTH-179190",
    "cr9b2_jiraurl": "https://jira.cc.bmwgroup.net/browse/PTH-179190",
    "cr9b2_name": "L2",
    "cr9b2_duedate": "02.06.2026 00:00",
    "cr9b2_ilevelnames": "[\"NA05-26-11-480\",\"NA06-26-11-480\",\"NA00-26-11-480\",\"G065-26-11-480\",\"G065-27-03-440\"]",
    "cr9b2_parentjiraissue": "PTH-179188",
    "cr9b2_parentbranches": "[\"PTH-06\"]",
    "cr9b2_brvs": "[]",
    "cr9b2_sops": "[]",
    "cr9b2_kw": "23",
    "cr9b2_year": "2.026",
    "cr9b2_yearweek": "2026-23"
  },
  {
    "_id": "0e044e20-023f-f111-bec6-7ced8d4a37b0",
    "cr9b2_jirakey": "PTH-173068",
    "cr9b2_jiraurl": "https://jira.cc.bmwgroup.net/browse/PTH-173068",
    "cr9b2_name": "L1_HV",
    "cr9b2_duedate": "09.04.2026 00:00",
    "cr9b2_ilevelnames": "[\"NA05-26-11-470\",\"NA06-26-11-470\",\"NA00-26-11-470\",\"G065-26-11-470\",\"G065-27-03-430\",\"NA00-27-03-430\",\"NA05-27-03-430\",\"NA06-27-03-430\",\"G065-27-07-380\",\"NA00-27-07-380\",\"NA05-27-07-380\",\"NA06-27-07-380\",\"RR45-27-07-380\",\"G065-27-11-340\",\"NA00-27-11-340\",\"NA05-27-11-340\",\"G065-28-03-300\",\"NA00-28-03-300\",\"NA06-28-03-300\",\"G065-28-07-250\",\"NA06-28-07-250\",\"G065-28-11-210\",\"NA05-28-11-210\",\"NA00-28-11-210\",\"NA05-29-03-170\",\"NA00-29-03-170\"]",
    "cr9b2_parentjiraissue": "PTH-173067",
    "cr9b2_parentbranches": "[\"PTH-06\"]",
    "cr9b2_brvs": "[]",
    "cr9b2_sops": "[]",
    "cr9b2_kw": "15",
    "cr9b2_year": "2.026",
    "cr9b2_yearweek": "2026-15"
  },
  {
    "_id": "0d044e20-023f-f111-bec6-7ced8d4a37b0",
    "cr9b2_jirakey": "PTH-170054",
    "cr9b2_jiraurl": "https://jira.cc.bmwgroup.net/browse/PTH-170054",
    "cr9b2_name": "L1_HV",
    "cr9b2_duedate": "05.03.2026 00:00",
    "cr9b2_ilevelnames": "[\"NA00-26-07-500\",\"NA05-26-07-500\"]",
    "cr9b2_parentjiraissue": "PTH-170053",
    "cr9b2_parentbranches": "[\"PTH-06\"]",
    "cr9b2_brvs": "[]",
    "cr9b2_sops": "[]",
    "cr9b2_kw": "10",
    "cr9b2_year": "2.026",
    "cr9b2_yearweek": "2026-10"
  },
  {
    "_id": "31a6e61e-023f-f111-bec6-7ced8d4a3506",
    "cr9b2_jirakey": "PTH-177952",
    "cr9b2_jiraurl": "https://jira.cc.bmwgroup.net/browse/PTH-177952",
    "cr9b2_name": "FB",
    "cr9b2_duedate": "07.04.2026 00:00",
    "cr9b2_ilevelnames": "[\"NA00-26-07-510\",\"NA05-26-07-510\"]",
    "cr9b2_parentjiraissue": "PTH-177948",
    "cr9b2_parentbranches": "[\"PTH-06\"]",
    "cr9b2_brvs": "[]",
    "cr9b2_sops": "[]",
    "cr9b2_kw": "15",
    "cr9b2_year": "2.026",
    "cr9b2_yearweek": "2026-15"
  },
  {
    "_id": "30a6e61e-023f-f111-bec6-7ced8d4a3506",
    "cr9b2_jirakey": "PTH-178790",
    "cr9b2_jiraurl": "https://jira.cc.bmwgroup.net/browse/PTH-178790",
    "cr9b2_name": "L2",
    "cr9b2_duedate": "19.05.2026 00:00",
    "cr9b2_ilevelnames": "[\"G065-26-11-480\",\"G065-27-03-450\",\"G065-27-07-400\",\"G065-27-11-360\",\"G065-28-03-320\",\"G065-28-07-270\",\"G065-28-11-230\",\"NA00-26-11-480\",\"NA00-27-03-450\",\"NA00-27-07-400\",\"NA00-27-11-360\",\"NA00-28-03-320\",\"NA00-28-11-230\",\"NA00-29-03-190\",\"NA05-26-11-480\",\"NA05-27-03-450\",\"NA05-27-07-400\",\"NA05-27-11-360\",\"NA05-28-11-230\",\"NA05-29-03-190\",\"NA06-26-11-480\",\"NA06-27-03-450\",\"NA06-27-07-400\",\"NA06-27-11-360\",\"NA06-28-03-320\",\"NA06-28-07-270\",\"RR45-27-07-400\"]",
    "cr9b2_parentjiraissue": "PTH-170497",
    "cr9b2_parentbranches": "[\"PTH-06\"]",
    "cr9b2_brvs": "[]",
    "cr9b2_sops": "[]",
    "cr9b2_kw": "21",
    "cr9b2_year": "2.026",
    "cr9b2_yearweek": "2026-21"
  },
  {
    "_id": "1aa6e61e-023f-f111-bec6-7ced8d4a3506",
    "cr9b2_jirakey": "PTH-162030",
    "cr9b2_jiraurl": "https://jira.cc.bmwgroup.net/browse/PTH-162030",
    "cr9b2_name": "FB",
    "cr9b2_duedate": "10.03.2026 00:00",
    "cr9b2_ilevelnames": "[\"G065-26-11-470\",\"G065-27-03-430\",\"G065-27-07-380\",\"G065-27-11-340\",\"G065-28-03-300\",\"G065-28-07-250\",\"G065-28-11-210\",\"NA00-26-11-470\",\"NA00-27-03-430\",\"NA00-27-07-380\",\"NA00-27-11-340\",\"NA00-28-03-300\",\"NA00-28-11-210\",\"NA00-29-03-170\",\"NA05-26-11-470\",\"NA05-27-03-430\",\"NA05-27-07-380\",\"NA05-27-11-340\",\"NA05-28-11-210\",\"NA05-29-03-170\",\"NA06-26-11-470\",\"NA06-27-03-430\",\"NA06-27-07-380\",\"NA06-28-03-300\",\"NA06-28-07-250\",\"RR45-27-07-380\"]",
    "cr9b2_parentjiraissue": "PTH-162026",
    "cr9b2_parentbranches": "[\"PTH-06\"]",
    "cr9b2_brvs": "[]",
    "cr9b2_sops": "[]",
    "cr9b2_kw": "11",
    "cr9b2_year": "2.026",
    "cr9b2_yearweek": "2026-11"
  },
  {
    "_id": "19a6e61e-023f-f111-bec6-7ced8d4a3506",
    "cr9b2_jirakey": "PTH-173070",
    "cr9b2_jiraurl": "https://jira.cc.bmwgroup.net/browse/PTH-173070",
    "cr9b2_name": "L3_HV",
    "cr9b2_duedate": "12.05.2026 00:00",
    "cr9b2_ilevelnames": "[\"NA05-26-11-470\",\"NA06-26-11-470\",\"NA00-26-11-470\",\"G065-26-11-470\",\"G065-27-03-430\",\"NA00-27-03-430\",\"NA05-27-03-430\",\"NA06-27-03-430\",\"G065-27-07-380\",\"NA00-27-07-380\",\"NA05-27-07-380\",\"NA06-27-07-380\",\"RR45-27-07-380\",\"G065-27-11-340\",\"NA00-27-11-340\",\"NA05-27-11-340\",\"G065-28-03-300\",\"NA00-28-03-300\",\"NA06-28-03-300\",\"G065-28-07-250\",\"NA06-28-07-250\",\"G065-28-11-210\",\"NA05-28-11-210\",\"NA00-28-11-210\",\"NA05-29-03-170\",\"NA00-29-03-170\"]",
    "cr9b2_parentjiraissue": "PTH-173067",
    "cr9b2_parentbranches": "[\"PTH-06\"]",
    "cr9b2_brvs": "[]",
    "cr9b2_sops": "[]",
    "cr9b2_kw": "20",
    "cr9b2_year": "2.026",
    "cr9b2_yearweek": "2026-20"
  },
  {
    "_id": "0ea6e61e-023f-f111-bec6-7ced8d4a3506",
    "cr9b2_jirakey": "PTH-162023",
    "cr9b2_jiraurl": "https://jira.cc.bmwgroup.net/browse/PTH-162023",
    "cr9b2_name": "L3_HV",
    "cr9b2_duedate": "21.04.2026 00:00",
    "cr9b2_ilevelnames": "[\"NA00-26-07-500\",\"NA05-26-07-500\",\"NA06-26-07-500\"]",
    "cr9b2_parentjiraissue": "PTH-162020",
    "cr9b2_parentbranches": "[\"PTH-06\"]",
    "cr9b2_brvs": "[]",
    "cr9b2_sops": "[]",
    "cr9b2_kw": "17",
    "cr9b2_year": "2.026",
    "cr9b2_yearweek": "2026-17"
  },
  {
    "_id": "0da6e61e-023f-f111-bec6-7ced8d4a3506",
    "cr9b2_jirakey": "PTH-162021",
    "cr9b2_jiraurl": "https://jira.cc.bmwgroup.net/browse/PTH-162021",
    "cr9b2_name": "L1_HV",
    "cr9b2_duedate": "12.03.2026 00:00",
    "cr9b2_ilevelnames": "[\"NA00-26-07-500\",\"NA05-26-07-500\",\"NA06-26-07-500\"]",
    "cr9b2_parentjiraissue": "PTH-162020",
    "cr9b2_parentbranches": "[\"PTH-06\"]",
    "cr9b2_brvs": "[]",
    "cr9b2_sops": "[]",
    "cr9b2_kw": "11",
    "cr9b2_year": "2.026",
    "cr9b2_yearweek": "2026-11"
  },
  {
    "_id": "8d606322-023f-f111-bec6-7ced8d4a3175",
    "cr9b2_jirakey": "PTH-179065",
    "cr9b2_jiraurl": "https://jira.cc.bmwgroup.net/browse/PTH-179065",
    "cr9b2_name": "FB",
    "cr9b2_duedate": "14.04.2026 00:00",
    "cr9b2_ilevelnames": "[\"NA00-26-07-510\",\"NA05-26-07-510\"]",
    "cr9b2_parentjiraissue": "PTH-179064",
    "cr9b2_parentbranches": "[\"PTH-06\"]",
    "cr9b2_brvs": "[]",
    "cr9b2_sops": "[]",
    "cr9b2_kw": "16",
    "cr9b2_year": "2.026",
    "cr9b2_yearweek": "2026-16"
  },
  {
    "_id": "8c606322-023f-f111-bec6-7ced8d4a3175",
    "cr9b2_jirakey": "PTH-177949",
    "cr9b2_jiraurl": "https://jira.cc.bmwgroup.net/browse/PTH-177949",
    "cr9b2_name": "L1_HV",
    "cr9b2_duedate": "09.04.2026 00:00",
    "cr9b2_ilevelnames": "[\"NA00-26-07-510\",\"NA05-26-07-510\"]",
    "cr9b2_parentjiraissue": "PTH-177948",
    "cr9b2_parentbranches": "[\"PTH-06\"]",
    "cr9b2_brvs": "[]",
    "cr9b2_sops": "[]",
    "cr9b2_kw": "15",
    "cr9b2_year": "2.026",
    "cr9b2_yearweek": "2026-15"
  },
  {
    "_id": "87606322-023f-f111-bec6-7ced8d4a3175",
    "cr9b2_jirakey": "PTH-176984",
    "cr9b2_jiraurl": "https://jira.cc.bmwgroup.net/browse/PTH-176984",
    "cr9b2_name": "L4",
    "cr9b2_duedate": "14.04.2026 00:00",
    "cr9b2_ilevelnames": "[\"NA05-26-03-540\"]",
    "cr9b2_parentjiraissue": "PTH-176982",
    "cr9b2_parentbranches": "[\"PTH-06\"]",
    "cr9b2_brvs": "[]",
    "cr9b2_sops": "[]",
    "cr9b2_kw": "16",
    "cr9b2_year": "2.026",
    "cr9b2_yearweek": "2026-16"
  },
  {
    "_id": "86606322-023f-f111-bec6-7ced8d4a3175",
    "cr9b2_jirakey": "PTH-176987",
    "cr9b2_jiraurl": "https://jira.cc.bmwgroup.net/browse/PTH-176987",
    "cr9b2_name": "L4",
    "cr9b2_duedate": "07.04.2026 00:00",
    "cr9b2_ilevelnames": "[\"NA05-26-03-540\"]",
    "cr9b2_parentjiraissue": "PTH-176982",
    "cr9b2_parentbranches": "[\"PTH-06\"]",
    "cr9b2_brvs": "[]",
    "cr9b2_sops": "[]",
    "cr9b2_kw": "15",
    "cr9b2_year": "2.026",
    "cr9b2_yearweek": "2026-15"
  },
  {
    "_id": "7d606322-023f-f111-bec6-7ced8d4a3175",
    "cr9b2_jirakey": "PTH-169588",
    "cr9b2_jiraurl": "https://jira.cc.bmwgroup.net/browse/PTH-169588",
    "cr9b2_name": "L3_HV",
    "cr9b2_duedate": "05.05.2026 00:00",
    "cr9b2_ilevelnames": "[\"NA05-26-11-470\",\"NA06-26-11-470\",\"NA00-26-11-470\",\"G065-26-11-470\",\"G065-27-03-430\",\"NA00-27-03-430\",\"NA05-27-03-430\",\"NA06-27-03-430\",\"G065-27-07-380\",\"NA00-27-07-380\",\"NA05-27-07-380\",\"NA06-27-07-380\",\"RR45-27-07-380\",\"G065-27-11-340\",\"NA00-27-11-340\",\"NA05-27-11-340\",\"G065-28-03-300\",\"NA00-28-03-300\",\"NA06-28-03-300\",\"G065-28-07-250\",\"NA06-28-07-250\",\"G065-28-11-210\",\"NA05-28-11-210\",\"NA00-28-11-210\",\"NA05-29-03-170\",\"NA00-29-03-170\"]",
    "cr9b2_parentjiraissue": "PTH-169585",
    "cr9b2_parentbranches": "[\"PTH-06\"]",
    "cr9b2_brvs": "[]",
    "cr9b2_sops": "[]",
    "cr9b2_kw": "19",
    "cr9b2_year": "2.026",
    "cr9b2_yearweek": "2026-19"
  },
  {
    "_id": "7c606322-023f-f111-bec6-7ced8d4a3175",
    "cr9b2_jirakey": "PTH-168714",
    "cr9b2_jiraurl": "https://jira.cc.bmwgroup.net/browse/PTH-168714",
    "cr9b2_name": "L3_HV",
    "cr9b2_duedate": "24.02.2026 00:00",
    "cr9b2_ilevelnames": "[\"G065-26-11-450\",\"G065-27-03-410\",\"G065-27-07-360\",\"G065-27-11-320\",\"G065-28-03-280\",\"G065-28-07-230\",\"NA00-26-07-480\",\"NA00-26-11-450\",\"NA00-27-03-410\",\"NA00-27-07-360\",\"NA00-27-11-320\",\"NA00-28-03-280\",\"NA00-28-11-190\",\"NA00-29-03-150\",\"NA05-26-07-480\",\"NA05-26-11-450\",\"NA05-27-03-410\",\"NA05-27-07-360\",\"NA05-27-11-320\",\"NA05-28-11-190\",\"NA05-29-03-150\",\"NA06-26-07-480\",\"NA06-26-11-450\",\"NA06-27-03-410\",\"NA06-27-07-360\",\"NA06-28-03-280\",\"NA06-28-07-230\",\"RR45-27-07-360\"]",
    "cr9b2_parentjiraissue": "PTH-168711",
    "cr9b2_parentbranches": "[\"PTH-06\"]",
    "cr9b2_brvs": "[]",
    "cr9b2_sops": "[]",
    "cr9b2_kw": "9",
    "cr9b2_year": "2.026",
    "cr9b2_yearweek": "2026-09"
  },
  {
    "_id": "79606322-023f-f111-bec6-7ced8d4a3175",
    "cr9b2_jirakey": "PTH-162013",
    "cr9b2_jiraurl": "https://jira.cc.bmwgroup.net/browse/PTH-162013",
    "cr9b2_name": "L1_HV",
    "cr9b2_duedate": "12.02.2026 00:00",
    "cr9b2_ilevelnames": "[\"G065-27-03-419\"]",
    "cr9b2_parentjiraissue": "PTH-162012",
    "cr9b2_parentbranches": "[\"PTH-06\"]",
    "cr9b2_brvs": "[]",
    "cr9b2_sops": "[]",
    "cr9b2_kw": "7",
    "cr9b2_year": "2.026",
    "cr9b2_yearweek": "2026-07"
  },
  {
    "_id": "86c63b21-023f-f111-bec6-7c1e52873f9b",
    "cr9b2_jirakey": "PTH-175765",
    "cr9b2_jiraurl": "https://jira.cc.bmwgroup.net/browse/PTH-175765",
    "cr9b2_name": "FB",
    "cr9b2_duedate": "17.03.2026 00:00",
    "cr9b2_ilevelnames": "[\"G065-26-11-459\",\"G065-27-03-419\",\"G065-27-07-369\"]",
    "cr9b2_parentjiraissue": "PTH-175764",
    "cr9b2_parentbranches": "[\"PTH-06\"]",
    "cr9b2_brvs": "[]",
    "cr9b2_sops": "[]",
    "cr9b2_kw": "12",
    "cr9b2_year": "2.026",
    "cr9b2_yearweek": "2026-12"
  },
  {
    "_id": "70c63b21-023f-f111-bec6-7c1e52873f9b",
    "cr9b2_jirakey": "PTH-180608",
    "cr9b2_jiraurl": "https://jira.cc.bmwgroup.net/browse/PTH-180608",
    "cr9b2_name": "L3",
    "cr9b2_duedate": "02.06.2026 00:00",
    "cr9b2_ilevelnames": "[\"NA06-26-11-510\",\"G065-27-03-470\",\"NA00-27-03-470\",\"NA05-27-03-470\",\"NA06-27-03-470\",\"G065-27-07-420\",\"NA00-27-07-420\",\"NA05-27-07-420\",\"NA06-27-07-420\",\"RR45-27-07-420\",\"G065-27-11-380\",\"NA00-27-11-380\",\"NA05-27-11-380\",\"NA06-27-11-380\",\"G065-28-03-340\",\"NA00-28-03-340\",\"NA06-28-03-340\",\"G065-28-07-290\",\"NA06-28-07-290\",\"G065-28-11-250\",\"NA05-28-11-250\",\"RR45-28-11-250\",\"NA00-28-11-250\",\"NA05-29-03-210\",\"NA00-29-03-210\"]",
    "cr9b2_parentjiraissue": "PTH-180605",
    "cr9b2_parentbranches": "[\"PTH-06\"]",
    "cr9b2_brvs": "[]",
    "cr9b2_sops": "[]",
    "cr9b2_kw": "23",
    "cr9b2_year": "2.026",
    "cr9b2_yearweek": "2026-23"
  },
  {
    "_id": "6dc63b21-023f-f111-bec6-7c1e52873f9b",
    "cr9b2_jirakey": "PTH-180609",
    "cr9b2_jiraurl": "https://jira.cc.bmwgroup.net/browse/PTH-180609",
    "cr9b2_name": "FB",
    "cr9b2_duedate": "05.05.2026 00:00",
    "cr9b2_ilevelnames": "[\"NA06-26-11-510\",\"G065-27-03-470\",\"NA00-27-03-470\",\"NA05-27-03-470\",\"NA06-27-03-470\",\"G065-27-07-420\",\"NA00-27-07-420\",\"NA05-27-07-420\",\"NA06-27-07-420\",\"RR45-27-07-420\",\"G065-27-11-380\",\"NA00-27-11-380\",\"NA05-27-11-380\",\"NA06-27-11-380\",\"G065-28-03-340\",\"NA00-28-03-340\",\"NA06-28-03-340\",\"G065-28-07-290\",\"NA06-28-07-290\",\"G065-28-11-250\",\"NA05-28-11-250\",\"RR45-28-11-250\",\"NA00-28-11-250\",\"NA05-29-03-210\",\"NA00-29-03-210\"]",
    "cr9b2_parentjiraissue": "PTH-180605",
    "cr9b2_parentbranches": "[\"PTH-06\"]",
    "cr9b2_brvs": "[]",
    "cr9b2_sops": "[]",
    "cr9b2_kw": "19",
    "cr9b2_year": "2.026",
    "cr9b2_yearweek": "2026-19"
  },
  {
    "_id": "67c63b21-023f-f111-bec6-7c1e52873f9b",
    "cr9b2_jirakey": "PTH-178787",
    "cr9b2_jiraurl": "https://jira.cc.bmwgroup.net/browse/PTH-178787",
    "cr9b2_name": "L4",
    "cr9b2_duedate": "21.04.2026 00:00",
    "cr9b2_ilevelnames": "[\"NA00-26-07-500\",\"NA05-26-07-500\"]",
    "cr9b2_parentjiraissue": "PTH-174075",
    "cr9b2_parentbranches": "[\"PTH-06\"]",
    "cr9b2_brvs": "[]",
    "cr9b2_sops": "[]",
    "cr9b2_kw": "17",
    "cr9b2_year": "2.026",
    "cr9b2_yearweek": "2026-17"
  },
  {
    "_id": "62c63b21-023f-f111-bec6-7c1e52873f9b",
    "cr9b2_jirakey": "PTH-177129",
    "cr9b2_jiraurl": "https://jira.cc.bmwgroup.net/browse/PTH-177129",
    "cr9b2_name": "FB",
    "cr9b2_duedate": "26.03.2026 00:00",
    "cr9b2_ilevelnames": "[\"NA05-26-03-540\"]",
    "cr9b2_parentjiraissue": "PTH-177128",
    "cr9b2_parentbranches": "[\"PTH-06\"]",
    "cr9b2_brvs": "[]",
    "cr9b2_sops": "[]",
    "cr9b2_kw": "13",
    "cr9b2_year": "2.026",
    "cr9b2_yearweek": "2026-13"
  },
  {
    "_id": "5ec63b21-023f-f111-bec6-7c1e52873f9b",
    "cr9b2_jirakey": "PTH-175577",
    "cr9b2_jiraurl": "https://jira.cc.bmwgroup.net/browse/PTH-175577",
    "cr9b2_name": "FB",
    "cr9b2_duedate": "07.04.2026 00:00",
    "cr9b2_ilevelnames": "[]",
    "cr9b2_parentjiraissue": "PTH-175576",
    "cr9b2_parentbranches": "[\"PTH-06\"]",
    "cr9b2_brvs": "[]",
    "cr9b2_sops": "[]",
    "cr9b2_kw": "15",
    "cr9b2_year": "2.026",
    "cr9b2_yearweek": "2026-15"
  },
  {
    "_id": "87c96921-023f-f111-bec6-0022489c44ec",
    "cr9b2_jirakey": "PTH-169586",
    "cr9b2_jiraurl": "https://jira.cc.bmwgroup.net/browse/PTH-169586",
    "cr9b2_name": "L1_HV",
    "cr9b2_duedate": "26.02.2026 00:00",
    "cr9b2_ilevelnames": "[\"NA05-26-11-470\",\"NA06-26-11-470\",\"NA00-26-11-470\",\"G065-26-11-470\",\"G065-27-03-430\",\"NA00-27-03-430\",\"NA05-27-03-430\",\"NA06-27-03-430\",\"G065-27-07-380\",\"NA00-27-07-380\",\"NA05-27-07-380\",\"NA06-27-07-380\",\"RR45-27-07-380\",\"G065-27-11-340\",\"NA00-27-11-340\",\"NA05-27-11-340\",\"G065-28-03-300\",\"NA00-28-03-300\",\"NA06-28-03-300\",\"G065-28-07-250\",\"NA06-28-07-250\",\"G065-28-11-210\",\"NA05-28-11-210\",\"NA00-28-11-210\",\"NA05-29-03-170\",\"NA00-29-03-170\"]",
    "cr9b2_parentjiraissue": "PTH-169585",
    "cr9b2_parentbranches": "[\"PTH-06\"]",
    "cr9b2_brvs": "[]",
    "cr9b2_sops": "[]",
    "cr9b2_kw": "9",
    "cr9b2_year": "2.026",
    "cr9b2_yearweek": "2026-09"
  },
  {
    "_id": "20044e20-023f-f111-bec6-7ced8d4a37b0",
    "cr9b2_jirakey": "PTH-174196",
    "cr9b2_jiraurl": "https://jira.cc.bmwgroup.net/browse/PTH-174196",
    "cr9b2_name": "L3_HV",
    "cr9b2_duedate": "07.04.2026 00:00",
    "cr9b2_ilevelnames": "[\"G065-26-11-459\",\"G065-27-03-419\",\"G065-27-07-369\"]",
    "cr9b2_parentjiraissue": "PTH-162412",
    "cr9b2_parentbranches": "[\"PTH-06\"]",
    "cr9b2_brvs": "[]",
    "cr9b2_sops": "[]",
    "cr9b2_kw": "15",
    "cr9b2_year": "2.026",
    "cr9b2_yearweek": "2026-15"
  },
  {
    "_id": "0f044e20-023f-f111-bec6-7ced8d4a37b0",
    "cr9b2_jirakey": "PTH-174078",
    "cr9b2_jiraurl": "https://jira.cc.bmwgroup.net/browse/PTH-174078",
    "cr9b2_name": "L3_HV",
    "cr9b2_duedate": "21.04.2026 00:00",
    "cr9b2_ilevelnames": "[\"NA00-26-07-500\",\"NA05-26-07-500\"]",
    "cr9b2_parentjiraissue": "PTH-174075",
    "cr9b2_parentbranches": "[\"PTH-06\"]",
    "cr9b2_brvs": "[]",
    "cr9b2_sops": "[]",
    "cr9b2_kw": "17",
    "cr9b2_year": "2.026",
    "cr9b2_yearweek": "2026-17"
  },
  {
    "_id": "c7bfe124-023f-f111-bec6-7ced8d4a3506",
    "cr9b2_jirakey": "PTH-178855",
    "cr9b2_jiraurl": "https://jira.cc.bmwgroup.net/browse/PTH-178855",
    "cr9b2_name": "FB",
    "cr9b2_duedate": "21.04.2026 00:00",
    "cr9b2_ilevelnames": "[\"G065-26-11-480\",\"NA00-26-11-480\",\"NA05-26-11-480\",\"NA06-26-11-480\"]",
    "cr9b2_parentjiraissue": "PTH-178850",
    "cr9b2_parentbranches": "[\"PTH-06\"]",
    "cr9b2_brvs": "[]",
    "cr9b2_sops": "[]",
    "cr9b2_kw": "17",
    "cr9b2_year": "2.026",
    "cr9b2_yearweek": "2026-17"
  },
  {
    "_id": "34a6e61e-023f-f111-bec6-7ced8d4a3506",
    "cr9b2_jirakey": "PTH-180388",
    "cr9b2_jiraurl": "https://jira.cc.bmwgroup.net/browse/PTH-180388",
    "cr9b2_name": "L3_HV",
    "cr9b2_duedate": "26.05.2026 00:00",
    "cr9b2_ilevelnames": "[\"NA00-26-07-510\",\"NA05-26-07-510\"]",
    "cr9b2_parentjiraissue": "PTH-177948",
    "cr9b2_parentbranches": "[\"PTH-06\"]",
    "cr9b2_brvs": "[]",
    "cr9b2_sops": "[]",
    "cr9b2_kw": "22",
    "cr9b2_year": "2.026",
    "cr9b2_yearweek": "2026-22"
  },
  {
    "_id": "2fa6e61e-023f-f111-bec6-7ced8d4a3506",
    "cr9b2_jirakey": "PTH-178851",
    "cr9b2_jiraurl": "https://jira.cc.bmwgroup.net/browse/PTH-178851",
    "cr9b2_name": "L1",
    "cr9b2_duedate": "23.04.2026 00:00",
    "cr9b2_ilevelnames": "[\"G065-26-11-480\",\"NA00-26-11-480\",\"NA05-26-11-480\",\"NA06-26-11-480\"]",
    "cr9b2_parentjiraissue": "PTH-178850",
    "cr9b2_parentbranches": "[\"PTH-06\"]",
    "cr9b2_brvs": "[]",
    "cr9b2_sops": "[]",
    "cr9b2_kw": "17",
    "cr9b2_year": "2.026",
    "cr9b2_yearweek": "2026-17"
  },
  {
    "_id": "2ea6e61e-023f-f111-bec6-7ced8d4a3506",
    "cr9b2_jirakey": "PTH-178792",
    "cr9b2_jiraurl": "https://jira.cc.bmwgroup.net/browse/PTH-178792",
    "cr9b2_name": "L3",
    "cr9b2_duedate": "02.06.2026 00:00",
    "cr9b2_ilevelnames": "[\"G065-26-11-480\",\"G065-27-03-450\",\"G065-27-07-400\",\"G065-27-11-360\",\"G065-28-03-320\",\"G065-28-07-270\",\"G065-28-11-230\",\"NA00-26-11-480\",\"NA00-27-03-450\",\"NA00-27-07-400\",\"NA00-27-11-360\",\"NA00-28-03-320\",\"NA00-28-11-230\",\"NA00-29-03-190\",\"NA05-26-11-480\",\"NA05-27-03-450\",\"NA05-27-07-400\",\"NA05-27-11-360\",\"NA05-28-11-230\",\"NA05-29-03-190\",\"NA06-26-11-480\",\"NA06-27-03-450\",\"NA06-27-07-400\",\"NA06-27-11-360\",\"NA06-28-03-320\",\"NA06-28-07-270\",\"RR45-27-07-400\"]",
    "cr9b2_parentjiraissue": "PTH-170497",
    "cr9b2_parentbranches": "[\"PTH-06\"]",
    "cr9b2_brvs": "[]",
    "cr9b2_sops": "[]",
    "cr9b2_kw": "23",
    "cr9b2_year": "2.026",
    "cr9b2_yearweek": "2026-23"
  },
  {
    "_id": "18a6e61e-023f-f111-bec6-7ced8d4a3506",
    "cr9b2_jirakey": "PTH-174076",
    "cr9b2_jiraurl": "https://jira.cc.bmwgroup.net/browse/PTH-174076",
    "cr9b2_name": "L1_HV",
    "cr9b2_duedate": "19.03.2026 00:00",
    "cr9b2_ilevelnames": "[\"NA00-26-07-500\",\"NA05-26-07-500\"]",
    "cr9b2_parentjiraissue": "PTH-174075",
    "cr9b2_parentbranches": "[\"PTH-06\"]",
    "cr9b2_brvs": "[]",
    "cr9b2_sops": "[]",
    "cr9b2_kw": "12",
    "cr9b2_year": "2.026",
    "cr9b2_yearweek": "2026-12"
  },
  {
    "_id": "17a6e61e-023f-f111-bec6-7ced8d4a3506",
    "cr9b2_jirakey": "PTH-174079",
    "cr9b2_jiraurl": "https://jira.cc.bmwgroup.net/browse/PTH-174079",
    "cr9b2_name": "FB",
    "cr9b2_duedate": "17.03.2026 00:00",
    "cr9b2_ilevelnames": "[\"NA00-26-07-500\",\"NA05-26-07-500\"]",
    "cr9b2_parentjiraissue": "PTH-174075",
    "cr9b2_parentbranches": "[\"PTH-06\"]",
    "cr9b2_brvs": "[]",
    "cr9b2_sops": "[]",
    "cr9b2_kw": "12",
    "cr9b2_year": "2.026",
    "cr9b2_yearweek": "2026-12"
  },
  {
    "_id": "06a6e61e-023f-f111-bec6-7ced8d4a3506",
    "cr9b2_jirakey": "PTH-162027",
    "cr9b2_jiraurl": "https://jira.cc.bmwgroup.net/browse/PTH-162027",
    "cr9b2_name": "L1_HV",
    "cr9b2_duedate": "12.03.2026 00:00",
    "cr9b2_ilevelnames": "[\"G065-26-11-470\",\"G065-27-03-430\",\"G065-27-07-380\",\"G065-27-11-340\",\"G065-28-03-300\",\"G065-28-07-250\",\"G065-28-11-210\",\"NA00-26-11-470\",\"NA00-27-03-430\",\"NA00-27-07-380\",\"NA00-27-11-340\",\"NA00-28-03-300\",\"NA00-28-11-210\",\"NA00-29-03-170\",\"NA05-26-11-470\",\"NA05-27-03-430\",\"NA05-27-07-380\",\"NA05-27-11-340\",\"NA05-28-11-210\",\"NA05-29-03-170\",\"NA06-26-11-470\",\"NA06-27-03-430\",\"NA06-27-07-380\",\"NA06-28-03-300\",\"NA06-28-07-250\",\"RR45-27-07-380\"]",
    "cr9b2_parentjiraissue": "PTH-162026",
    "cr9b2_parentbranches": "[\"PTH-06\"]",
    "cr9b2_brvs": "[]",
    "cr9b2_sops": "[]",
    "cr9b2_kw": "11",
    "cr9b2_year": "2.026",
    "cr9b2_yearweek": "2026-11"
  },
  {
    "_id": "90606322-023f-f111-bec6-7ced8d4a3175",
    "cr9b2_jirakey": "PTH-180607",
    "cr9b2_jiraurl": "https://jira.cc.bmwgroup.net/browse/PTH-180607",
    "cr9b2_name": "L2",
    "cr9b2_duedate": "19.05.2026 00:00",
    "cr9b2_ilevelnames": "[\"NA06-26-11-510\",\"G065-27-03-470\",\"NA00-27-03-470\",\"NA05-27-03-470\",\"NA06-27-03-470\",\"G065-27-07-420\",\"NA00-27-07-420\",\"NA05-27-07-420\",\"NA06-27-07-420\",\"RR45-27-07-420\",\"G065-27-11-380\",\"NA00-27-11-380\",\"NA05-27-11-380\",\"NA06-27-11-380\",\"G065-28-03-340\",\"NA00-28-03-340\",\"NA06-28-03-340\",\"G065-28-07-290\",\"NA06-28-07-290\",\"G065-28-11-250\",\"NA05-28-11-250\",\"RR45-28-11-250\",\"NA00-28-11-250\",\"NA05-29-03-210\",\"NA00-29-03-210\"]",
    "cr9b2_parentjiraissue": "PTH-180605",
    "cr9b2_parentbranches": "[\"PTH-06\"]",
    "cr9b2_brvs": "[]",
    "cr9b2_sops": "[]",
    "cr9b2_kw": "21",
    "cr9b2_year": "2.026",
    "cr9b2_yearweek": "2026-21"
  },
  {
    "_id": "8b606322-023f-f111-bec6-7ced8d4a3175",
    "cr9b2_jirakey": "PTH-179189",
    "cr9b2_jiraurl": "https://jira.cc.bmwgroup.net/browse/PTH-179189",
    "cr9b2_name": "L1",
    "cr9b2_duedate": "04.06.2026 00:00",
    "cr9b2_ilevelnames": "[\"NA05-26-11-480\",\"NA06-26-11-480\",\"NA00-26-11-480\",\"G065-26-11-480\",\"G065-27-03-440\"]",
    "cr9b2_parentjiraissue": "PTH-179188",
    "cr9b2_parentbranches": "[\"PTH-06\"]",
    "cr9b2_brvs": "[]",
    "cr9b2_sops": "[]",
    "cr9b2_kw": "23",
    "cr9b2_year": "2.026",
    "cr9b2_yearweek": "2026-23"
  },
  {
    "_id": "8a606322-023f-f111-bec6-7ced8d4a3175",
    "cr9b2_jirakey": "PTH-179191",
    "cr9b2_jiraurl": "https://jira.cc.bmwgroup.net/browse/PTH-179191",
    "cr9b2_name": "L3",
    "cr9b2_duedate": "02.06.2026 00:00",
    "cr9b2_ilevelnames": "[\"NA05-26-11-480\",\"NA06-26-11-480\",\"NA00-26-11-480\",\"G065-26-11-480\",\"G065-27-03-440\"]",
    "cr9b2_parentjiraissue": "PTH-179188",
    "cr9b2_parentbranches": "[\"PTH-06\"]",
    "cr9b2_brvs": "[]",
    "cr9b2_sops": "[]",
    "cr9b2_kw": "23",
    "cr9b2_year": "2.026",
    "cr9b2_yearweek": "2026-23"
  },
  {
    "_id": "84606322-023f-f111-bec6-7ced8d4a3175",
    "cr9b2_jirakey": "PTH-173069",
    "cr9b2_jiraurl": "https://jira.cc.bmwgroup.net/browse/PTH-173069",
    "cr9b2_name": "L2_HV",
    "cr9b2_duedate": "21.04.2026 00:00",
    "cr9b2_ilevelnames": "[\"NA05-26-11-470\",\"NA06-26-11-470\",\"NA00-26-11-470\",\"G065-26-11-470\",\"G065-27-03-430\",\"NA00-27-03-430\",\"NA05-27-03-430\",\"NA06-27-03-430\",\"G065-27-07-380\",\"NA00-27-07-380\",\"NA05-27-07-380\",\"NA06-27-07-380\",\"RR45-27-07-380\",\"G065-27-11-340\",\"NA00-27-11-340\",\"NA05-27-11-340\",\"G065-28-03-300\",\"NA00-28-03-300\",\"NA06-28-03-300\",\"G065-28-07-250\",\"NA06-28-07-250\",\"G065-28-11-210\",\"NA05-28-11-210\",\"NA00-28-11-210\",\"NA05-29-03-170\",\"NA00-29-03-170\"]",
    "cr9b2_parentjiraissue": "PTH-173067",
    "cr9b2_parentbranches": "[\"PTH-06\"]",
    "cr9b2_brvs": "[]",
    "cr9b2_sops": "[]",
    "cr9b2_kw": "17",
    "cr9b2_year": "2.026",
    "cr9b2_yearweek": "2026-17"
  },
  {
    "_id": "83606322-023f-f111-bec6-7ced8d4a3175",
    "cr9b2_jirakey": "PTH-173142",
    "cr9b2_jiraurl": "https://jira.cc.bmwgroup.net/browse/PTH-173142",
    "cr9b2_name": "FB",
    "cr9b2_duedate": "03.03.2026 00:00",
    "cr9b2_ilevelnames": "[\"NA06-26-11-450\",\"NA06-27-03-410\",\"NA06-27-07-360\",\"NA06-28-03-280\",\"NA06-28-07-230\"]",
    "cr9b2_parentjiraissue": "PTH-173141",
    "cr9b2_parentbranches": "[\"PTH-06\"]",
    "cr9b2_brvs": "[]",
    "cr9b2_sops": "[]",
    "cr9b2_kw": "10",
    "cr9b2_year": "2.026",
    "cr9b2_yearweek": "2026-10"
  },
  {
    "_id": "7b606322-023f-f111-bec6-7ced8d4a3175",
    "cr9b2_jirakey": "PTH-166736",
    "cr9b2_jiraurl": "https://jira.cc.bmwgroup.net/browse/PTH-166736",
    "cr9b2_name": "L3_HV",
    "cr9b2_duedate": "24.02.2026 00:00",
    "cr9b2_ilevelnames": "[\"NA05-26-07-460\",\"NA06-26-07-460\",\"NA00-26-07-460\",\"G065-26-07-460\",\"G065-26-11-420\",\"NA00-26-11-420\",\"NA05-26-11-420\",\"NA06-26-11-420\",\"G065-27-03-380\",\"NA00-27-03-380\",\"NA05-27-03-380\",\"NA06-27-03-380\",\"G065-27-07-330\",\"NA00-27-07-330\",\"NA05-27-07-330\",\"NA06-27-07-330\",\"RR45-27-07-330\",\"G065-27-11-290\",\"NA00-27-11-290\",\"NA05-27-11-290\",\"G065-28-03-250\",\"NA00-28-03-250\",\"NA06-28-03-250\",\"G065-28-07-200\",\"NA06-28-07-200\",\"NA05-28-11-160\",\"NA05-29-03-120\"]",
    "cr9b2_parentjiraissue": "PTH-147054",
    "cr9b2_parentbranches": "[\"PTH-06\"]",
    "cr9b2_brvs": "[]",
    "cr9b2_sops": "[]",
    "cr9b2_kw": "9",
    "cr9b2_year": "2.026",
    "cr9b2_yearweek": "2026-09"
  },
  {
    "_id": "7a606322-023f-f111-bec6-7ced8d4a3175",
    "cr9b2_jirakey": "PTH-162004",
    "cr9b2_jiraurl": "https://jira.cc.bmwgroup.net/browse/PTH-162004",
    "cr9b2_name": "L1_HV",
    "cr9b2_duedate": "12.02.2026 00:00",
    "cr9b2_ilevelnames": "[\"NA00-26-07-490\",\"NA05-26-07-490\",\"NA06-26-07-490\"]",
    "cr9b2_parentjiraissue": "PTH-162003",
    "cr9b2_parentbranches": "[\"PTH-06\"]",
    "cr9b2_brvs": "[]",
    "cr9b2_sops": "[]",
    "cr9b2_kw": "7",
    "cr9b2_year": "2.026",
    "cr9b2_yearweek": "2026-07"
  },
  {
    "_id": "78606322-023f-f111-bec6-7ced8d4a3175",
    "cr9b2_jirakey": "PTH-162015",
    "cr9b2_jiraurl": "https://jira.cc.bmwgroup.net/browse/PTH-162015",
    "cr9b2_name": "L3_HV",
    "cr9b2_duedate": "10.03.2026 00:00",
    "cr9b2_ilevelnames": "[\"G065-27-03-419\"]",
    "cr9b2_parentjiraissue": "PTH-162012",
    "cr9b2_parentbranches": "[\"PTH-06\"]",
    "cr9b2_brvs": "[]",
    "cr9b2_sops": "[]",
    "cr9b2_kw": "11",
    "cr9b2_year": "2.026",
    "cr9b2_yearweek": "2026-11"
  },
  {
    "_id": "84c63b21-023f-f111-bec6-7c1e52873f9b",
    "cr9b2_jirakey": "PTH-174077",
    "cr9b2_jiraurl": "https://jira.cc.bmwgroup.net/browse/PTH-174077",
    "cr9b2_name": "L2_HV",
    "cr9b2_duedate": "24.03.2026 00:00",
    "cr9b2_ilevelnames": "[\"NA00-26-07-500\",\"NA05-26-07-500\"]",
    "cr9b2_parentjiraissue": "PTH-174075",
    "cr9b2_parentbranches": "[\"PTH-06\"]",
    "cr9b2_brvs": "[]",
    "cr9b2_sops": "[]",
    "cr9b2_kw": "13",
    "cr9b2_year": "2.026",
    "cr9b2_yearweek": "2026-13"
  },
  {
    "_id": "6ec63b21-023f-f111-bec6-7c1e52873f9b",
    "cr9b2_jirakey": "PTH-180457",
    "cr9b2_jiraurl": "https://jira.cc.bmwgroup.net/browse/PTH-180457",
    "cr9b2_name": "L2",
    "cr9b2_duedate": "26.05.2026 00:00",
    "cr9b2_ilevelnames": "[\"G065-26-11-480\",\"G065-27-03-450\",\"G065-27-07-400\",\"G065-27-11-360\",\"G065-28-03-320\",\"G065-28-07-270\",\"G065-28-11-230\",\"NA00-26-11-480\",\"NA00-27-03-450\",\"NA00-27-07-400\",\"NA00-27-11-360\",\"NA00-28-03-320\",\"NA00-28-11-230\",\"NA00-29-03-190\",\"NA05-26-11-480\",\"NA05-27-03-450\",\"NA05-27-07-400\",\"NA05-27-11-360\",\"NA05-28-11-230\",\"NA05-29-03-190\",\"NA06-26-11-480\",\"NA06-27-03-450\",\"NA06-27-07-400\",\"NA06-27-11-360\",\"NA06-28-03-320\",\"NA06-28-07-270\",\"RR45-27-07-400\"]",
    "cr9b2_parentjiraissue": "PTH-170497",
    "cr9b2_parentbranches": "[\"PTH-06\"]",
    "cr9b2_brvs": "[]",
    "cr9b2_sops": "[]",
    "cr9b2_kw": "22",
    "cr9b2_year": "2.026",
    "cr9b2_yearweek": "2026-22"
  },
  {
    "_id": "69c63b21-023f-f111-bec6-7c1e52873f9b",
    "cr9b2_jirakey": "PTH-178853",
    "cr9b2_jiraurl": "https://jira.cc.bmwgroup.net/browse/PTH-178853",
    "cr9b2_name": "L3",
    "cr9b2_duedate": "02.06.2026 00:00",
    "cr9b2_ilevelnames": "[\"G065-26-11-480\",\"NA00-26-11-480\",\"NA05-26-11-480\",\"NA06-26-11-480\"]",
    "cr9b2_parentjiraissue": "PTH-178850",
    "cr9b2_parentbranches": "[\"PTH-06\"]",
    "cr9b2_brvs": "[]",
    "cr9b2_sops": "[]",
    "cr9b2_kw": "23",
    "cr9b2_year": "2.026",
    "cr9b2_yearweek": "2026-23"
  },
  {
    "_id": "64c63b21-023f-f111-bec6-7c1e52873f9b",
    "cr9b2_jirakey": "PTH-177506",
    "cr9b2_jiraurl": "https://jira.cc.bmwgroup.net/browse/PTH-177506",
    "cr9b2_name": "FB",
    "cr9b2_duedate": "31.03.2026 00:00",
    "cr9b2_ilevelnames": "[\"G065-26-11-459\",\"G065-27-03-419\",\"G065-27-07-369\"]",
    "cr9b2_parentjiraissue": "PTH-177505",
    "cr9b2_parentbranches": "[\"PTH-06\"]",
    "cr9b2_brvs": "[]",
    "cr9b2_sops": "[]",
    "cr9b2_kw": "14",
    "cr9b2_year": "2.026",
    "cr9b2_yearweek": "2026-14"
  },
  {
    "_id": "5fc63b21-023f-f111-bec6-7c1e52873f9b",
    "cr9b2_jirakey": "PTH-175184",
    "cr9b2_jiraurl": "https://jira.cc.bmwgroup.net/browse/PTH-175184",
    "cr9b2_name": "L4",
    "cr9b2_duedate": "07.04.2026 00:00",
    "cr9b2_ilevelnames": "[\"NA05-26-03-530\"]",
    "cr9b2_parentjiraissue": "PTH-168041",
    "cr9b2_parentbranches": "[\"PTH-06\"]",
    "cr9b2_brvs": "[]",
    "cr9b2_sops": "[]",
    "cr9b2_kw": "15",
    "cr9b2_year": "2.026",
    "cr9b2_yearweek": "2026-15"
  },
  {
    "_id": "3dc63b21-023f-f111-bec6-7c1e52873f9b",
    "cr9b2_jirakey": "PTH-173061",
    "cr9b2_jiraurl": "https://jira.cc.bmwgroup.net/browse/PTH-173061",
    "cr9b2_name": "L3_HV",
    "cr9b2_duedate": "17.03.2026 00:00",
    "cr9b2_ilevelnames": "[\"NA06-26-07-490\"]",
    "cr9b2_parentjiraissue": "PTH-173058",
    "cr9b2_parentbranches": "[\"PTH-06\"]",
    "cr9b2_brvs": "[]",
    "cr9b2_sops": "[]",
    "cr9b2_kw": "12",
    "cr9b2_year": "2.026",
    "cr9b2_yearweek": "2026-12"
  },
  {
    "_id": "17c63b21-023f-f111-bec6-7c1e52873f9b",
    "cr9b2_jirakey": "PTH-162024",
    "cr9b2_jiraurl": "https://jira.cc.bmwgroup.net/browse/PTH-162024",
    "cr9b2_name": "FB",
    "cr9b2_duedate": "10.03.2026 00:00",
    "cr9b2_ilevelnames": "[\"NA00-26-07-500\",\"NA05-26-07-500\",\"NA06-26-07-500\"]",
    "cr9b2_parentjiraissue": "PTH-162020",
    "cr9b2_parentbranches": "[\"PTH-06\"]",
    "cr9b2_brvs": "[]",
    "cr9b2_sops": "[]",
    "cr9b2_kw": "11",
    "cr9b2_year": "2.026",
    "cr9b2_yearweek": "2026-11"
  },
  {
    "_id": "0c044e20-023f-f111-bec6-7ced8d4a37b0",
    "cr9b2_jirakey": "PTH-170057",
    "cr9b2_jiraurl": "https://jira.cc.bmwgroup.net/browse/PTH-170057",
    "cr9b2_name": "FB",
    "cr9b2_duedate": "03.03.2026 00:00",
    "cr9b2_ilevelnames": "[\"NA00-26-07-500\",\"NA05-26-07-500\"]",
    "cr9b2_parentjiraissue": "PTH-170053",
    "cr9b2_parentbranches": "[\"PTH-06\"]",
    "cr9b2_brvs": "[]",
    "cr9b2_sops": "[]",
    "cr9b2_kw": "10",
    "cr9b2_year": "2.026",
    "cr9b2_yearweek": "2026-10"
  },
  {
    "_id": "0b044e20-023f-f111-bec6-7ced8d4a37b0",
    "cr9b2_jirakey": "PTH-168052",
    "cr9b2_jiraurl": "https://jira.cc.bmwgroup.net/browse/PTH-168052",
    "cr9b2_name": "L4",
    "cr9b2_duedate": "12.03.2026 00:00",
    "cr9b2_ilevelnames": "[\"NA05-26-03-530\"]",
    "cr9b2_parentjiraissue": "PTH-168041",
    "cr9b2_parentbranches": "[\"PTH-06\"]",
    "cr9b2_brvs": "[]",
    "cr9b2_sops": "[]",
    "cr9b2_kw": "11",
    "cr9b2_year": "2.026",
    "cr9b2_yearweek": "2026-11"
  },
  {
    "_id": "0a044e20-023f-f111-bec6-7ced8d4a37b0",
    "cr9b2_jirakey": "PTH-162028",
    "cr9b2_jiraurl": "https://jira.cc.bmwgroup.net/browse/PTH-162028",
    "cr9b2_name": "L2_HV",
    "cr9b2_duedate": "24.03.2026 00:00",
    "cr9b2_ilevelnames": "[\"G065-26-11-470\",\"G065-27-03-430\",\"G065-27-07-380\",\"G065-27-11-340\",\"G065-28-03-300\",\"G065-28-07-250\",\"G065-28-11-210\",\"NA00-26-11-470\",\"NA00-27-03-430\",\"NA00-27-07-380\",\"NA00-27-11-340\",\"NA00-28-03-300\",\"NA00-28-11-210\",\"NA00-29-03-170\",\"NA05-26-11-470\",\"NA05-27-03-430\",\"NA05-27-07-380\",\"NA05-27-11-340\",\"NA05-28-11-210\",\"NA05-29-03-170\",\"NA06-26-11-470\",\"NA06-27-03-430\",\"NA06-27-07-380\",\"NA06-28-03-300\",\"NA06-28-07-250\",\"RR45-27-07-380\"]",
    "cr9b2_parentjiraissue": "PTH-162026",
    "cr9b2_parentbranches": "[\"PTH-06\"]",
    "cr9b2_brvs": "[]",
    "cr9b2_sops": "[]",
    "cr9b2_kw": "13",
    "cr9b2_year": "2.026",
    "cr9b2_yearweek": "2026-13"
  },
  {
    "_id": "09044e20-023f-f111-bec6-7ced8d4a37b0",
    "cr9b2_jirakey": "PTH-165704",
    "cr9b2_jiraurl": "https://jira.cc.bmwgroup.net/browse/PTH-165704",
    "cr9b2_name": "L2_HV",
    "cr9b2_duedate": "12.02.2026 00:00",
    "cr9b2_ilevelnames": "[\"G065-26-11-450\",\"G065-27-03-410\",\"G065-27-07-360\",\"G065-27-11-320\",\"G065-28-03-280\",\"G065-28-07-230\",\"NA00-26-07-480\",\"NA00-26-11-450\",\"NA00-27-03-410\",\"NA00-27-07-360\",\"NA00-27-11-320\",\"NA00-28-03-280\",\"NA00-28-11-190\",\"NA00-29-03-150\",\"NA05-26-07-480\",\"NA05-26-11-450\",\"NA05-27-03-410\",\"NA05-27-07-360\",\"NA05-27-11-320\",\"NA05-28-11-190\",\"NA05-29-03-150\",\"NA06-26-07-480\",\"NA06-26-11-450\",\"NA06-27-03-410\",\"NA06-27-07-360\",\"NA06-28-03-280\",\"NA06-28-07-230\",\"RR45-27-07-360\"]",
    "cr9b2_parentjiraissue": "PTH-165702",
    "cr9b2_parentbranches": "[\"PTH-06\"]",
    "cr9b2_brvs": "[]",
    "cr9b2_sops": "[]",
    "cr9b2_kw": "7",
    "cr9b2_year": "2.026",
    "cr9b2_yearweek": "2026-07"
  },
  {
    "_id": "33a6e61e-023f-f111-bec6-7ced8d4a3506",
    "cr9b2_jirakey": "PTH-180606",
    "cr9b2_jiraurl": "https://jira.cc.bmwgroup.net/browse/PTH-180606",
    "cr9b2_name": "L1",
    "cr9b2_duedate": "07.05.2026 00:00",
    "cr9b2_ilevelnames": "[\"NA06-26-11-510\",\"G065-27-03-470\",\"NA00-27-03-470\",\"NA05-27-03-470\",\"NA06-27-03-470\",\"G065-27-07-420\",\"NA00-27-07-420\",\"NA05-27-07-420\",\"NA06-27-07-420\",\"RR45-27-07-420\",\"G065-27-11-380\",\"NA00-27-11-380\",\"NA05-27-11-380\",\"NA06-27-11-380\",\"G065-28-03-340\",\"NA00-28-03-340\",\"NA06-28-03-340\",\"G065-28-07-290\",\"NA06-28-07-290\",\"G065-28-11-250\",\"NA05-28-11-250\",\"RR45-28-11-250\",\"NA00-28-11-250\",\"NA05-29-03-210\",\"NA00-29-03-210\"]",
    "cr9b2_parentjiraissue": "PTH-180605",
    "cr9b2_parentbranches": "[\"PTH-06\"]",
    "cr9b2_brvs": "[]",
    "cr9b2_sops": "[]",
    "cr9b2_kw": "19",
    "cr9b2_year": "2.026",
    "cr9b2_yearweek": "2026-19"
  },
  {
    "_id": "32a6e61e-023f-f111-bec6-7ced8d4a3506",
    "cr9b2_jirakey": "PTH-180390",
    "cr9b2_jiraurl": "https://jira.cc.bmwgroup.net/browse/PTH-180390",
    "cr9b2_name": "L3_HV",
    "cr9b2_duedate": "26.05.2026 00:00",
    "cr9b2_ilevelnames": "[\"NA05-26-11-470\",\"NA06-26-11-470\",\"NA00-26-11-470\",\"G065-26-11-470\",\"G065-27-03-430\",\"NA00-27-03-430\",\"NA05-27-03-430\",\"NA06-27-03-430\",\"G065-27-07-380\",\"NA00-27-07-380\",\"NA05-27-07-380\",\"NA06-27-07-380\",\"RR45-27-07-380\",\"G065-27-11-340\",\"NA00-27-11-340\",\"NA05-27-11-340\",\"G065-28-03-300\",\"NA00-28-03-300\",\"NA06-28-03-300\",\"G065-28-07-250\",\"NA06-28-07-250\",\"G065-28-11-210\",\"NA05-28-11-210\",\"NA00-28-11-210\",\"NA05-29-03-170\",\"NA00-29-03-170\"]",
    "cr9b2_parentjiraissue": "PTH-173067",
    "cr9b2_parentbranches": "[\"PTH-06\"]",
    "cr9b2_brvs": "[]",
    "cr9b2_sops": "[]",
    "cr9b2_kw": "22",
    "cr9b2_year": "2.026",
    "cr9b2_yearweek": "2026-22"
  },
  {
    "_id": "2da6e61e-023f-f111-bec6-7ced8d4a3506",
    "cr9b2_jirakey": "PTH-176309",
    "cr9b2_jiraurl": "https://jira.cc.bmwgroup.net/browse/PTH-176309",
    "cr9b2_name": "FB",
    "cr9b2_duedate": "31.03.2026 00:00",
    "cr9b2_ilevelnames": "[\"G065-26-11-459\",\"G065-27-03-419\",\"G065-27-07-369\"]",
    "cr9b2_parentjiraissue": "PTH-176308",
    "cr9b2_parentbranches": "[\"PTH-06\"]",
    "cr9b2_brvs": "[]",
    "cr9b2_sops": "[]",
    "cr9b2_kw": "14",
    "cr9b2_year": "2.026",
    "cr9b2_yearweek": "2026-14"
  },
  {
    "_id": "1ba6e61e-023f-f111-bec6-7ced8d4a3506",
    "cr9b2_jirakey": "PTH-168871",
    "cr9b2_jiraurl": "https://jira.cc.bmwgroup.net/browse/PTH-168871",
    "cr9b2_name": "L2_HV",
    "cr9b2_duedate": "23.02.2026 00:00",
    "cr9b2_ilevelnames": "[\"NA00-26-07-490\",\"NA05-26-07-490\",\"NA06-26-07-490\"]",
    "cr9b2_parentjiraissue": "PTH-168337",
    "cr9b2_parentbranches": "[\"PTH-06\"]",
    "cr9b2_brvs": "[]",
    "cr9b2_sops": "[]",
    "cr9b2_kw": "9",
    "cr9b2_year": "2.026",
    "cr9b2_yearweek": "2026-09"
  },
  {
    "_id": "16a6e61e-023f-f111-bec6-7ced8d4a3506",
    "cr9b2_jirakey": "PTH-170055",
    "cr9b2_jiraurl": "https://jira.cc.bmwgroup.net/browse/PTH-170055",
    "cr9b2_name": "L2_HV",
    "cr9b2_duedate": "24.03.2026 00:00",
    "cr9b2_ilevelnames": "[\"NA00-26-07-500\",\"NA05-26-07-500\"]",
    "cr9b2_parentjiraissue": "PTH-170053",
    "cr9b2_parentbranches": "[\"PTH-06\"]",
    "cr9b2_brvs": "[]",
    "cr9b2_sops": "[]",
    "cr9b2_kw": "13",
    "cr9b2_year": "2.026",
    "cr9b2_yearweek": "2026-13"
  },
  {
    "_id": "14a6e61e-023f-f111-bec6-7ced8d4a3506",
    "cr9b2_jirakey": "PTH-173062",
    "cr9b2_jiraurl": "https://jira.cc.bmwgroup.net/browse/PTH-173062",
    "cr9b2_name": "FB",
    "cr9b2_duedate": "03.03.2026 00:00",
    "cr9b2_ilevelnames": "[\"NA06-26-07-490\"]",
    "cr9b2_parentjiraissue": "PTH-173058",
    "cr9b2_parentbranches": "[\"PTH-06\"]",
    "cr9b2_brvs": "[]",
    "cr9b2_sops": "[]",
    "cr9b2_kw": "10",
    "cr9b2_year": "2.026",
    "cr9b2_yearweek": "2026-10"
  },
  {
    "_id": "13a6e61e-023f-f111-bec6-7ced8d4a3506",
    "cr9b2_jirakey": "PTH-170056",
    "cr9b2_jiraurl": "https://jira.cc.bmwgroup.net/browse/PTH-170056",
    "cr9b2_name": "L3_HV",
    "cr9b2_duedate": "07.04.2026 00:00",
    "cr9b2_ilevelnames": "[\"NA00-26-07-500\",\"NA05-26-07-500\"]",
    "cr9b2_parentjiraissue": "PTH-170053",
    "cr9b2_parentbranches": "[\"PTH-06\"]",
    "cr9b2_brvs": "[]",
    "cr9b2_sops": "[]",
    "cr9b2_kw": "15",
    "cr9b2_year": "2.026",
    "cr9b2_yearweek": "2026-15"
  },
  {
    "_id": "12a6e61e-023f-f111-bec6-7ced8d4a3506",
    "cr9b2_jirakey": "PTH-169587",
    "cr9b2_jiraurl": "https://jira.cc.bmwgroup.net/browse/PTH-169587",
    "cr9b2_name": "L2_HV",
    "cr9b2_duedate": "24.03.2026 00:00",
    "cr9b2_ilevelnames": "[\"NA05-26-11-470\",\"NA06-26-11-470\",\"NA00-26-11-470\",\"G065-26-11-470\",\"G065-27-03-430\",\"NA00-27-03-430\",\"NA05-27-03-430\",\"NA06-27-03-430\",\"G065-27-07-380\",\"NA00-27-07-380\",\"NA05-27-07-380\",\"NA06-27-07-380\",\"RR45-27-07-380\",\"G065-27-11-340\",\"NA00-27-11-340\",\"NA05-27-11-340\",\"G065-28-03-300\",\"NA00-28-03-300\",\"NA06-28-03-300\",\"G065-28-07-250\",\"NA06-28-07-250\",\"G065-28-11-210\",\"NA05-28-11-210\",\"NA00-28-11-210\",\"NA05-29-03-170\",\"NA00-29-03-170\"]",
    "cr9b2_parentjiraissue": "PTH-169585",
    "cr9b2_parentbranches": "[\"PTH-06\"]",
    "cr9b2_brvs": "[]",
    "cr9b2_sops": "[]",
    "cr9b2_kw": "13",
    "cr9b2_year": "2.026",
    "cr9b2_yearweek": "2026-13"
  },
  {
    "_id": "8f606322-023f-f111-bec6-7ced8d4a3175",
    "cr9b2_jirakey": "PTH-177951",
    "cr9b2_jiraurl": "https://jira.cc.bmwgroup.net/browse/PTH-177951",
    "cr9b2_name": "L3_HV",
    "cr9b2_duedate": "12.05.2026 00:00",
    "cr9b2_ilevelnames": "[\"NA00-26-07-510\",\"NA05-26-07-510\"]",
    "cr9b2_parentjiraissue": "PTH-177948",
    "cr9b2_parentbranches": "[\"PTH-06\"]",
    "cr9b2_brvs": "[]",
    "cr9b2_sops": "[]",
    "cr9b2_kw": "20",
    "cr9b2_year": "2.026",
    "cr9b2_yearweek": "2026-20"
  },
  {
    "_id": "8e606322-023f-f111-bec6-7ced8d4a3175",
    "cr9b2_jirakey": "PTH-180610",
    "cr9b2_jiraurl": "https://jira.cc.bmwgroup.net/browse/PTH-180610",
    "cr9b2_name": "L2",
    "cr9b2_duedate": "26.05.2026 00:00",
    "cr9b2_ilevelnames": "[\"NA06-26-11-510\",\"G065-27-03-470\",\"NA00-27-03-470\",\"NA05-27-03-470\",\"NA06-27-03-470\",\"G065-27-07-420\",\"NA00-27-07-420\",\"NA05-27-07-420\",\"NA06-27-07-420\",\"RR45-27-07-420\",\"G065-27-11-380\",\"NA00-27-11-380\",\"NA05-27-11-380\",\"NA06-27-11-380\",\"G065-28-03-340\",\"NA00-28-03-340\",\"NA06-28-03-340\",\"G065-28-07-290\",\"NA06-28-07-290\",\"G065-28-11-250\",\"NA05-28-11-250\",\"RR45-28-11-250\",\"NA00-28-11-250\",\"NA05-29-03-210\",\"NA00-29-03-210\"]",
    "cr9b2_parentjiraissue": "PTH-180605",
    "cr9b2_parentbranches": "[\"PTH-06\"]",
    "cr9b2_brvs": "[]",
    "cr9b2_sops": "[]",
    "cr9b2_kw": "22",
    "cr9b2_year": "2.026",
    "cr9b2_yearweek": "2026-22"
  },
  {
    "_id": "89606322-023f-f111-bec6-7ced8d4a3175",
    "cr9b2_jirakey": "PTH-177950",
    "cr9b2_jiraurl": "https://jira.cc.bmwgroup.net/browse/PTH-177950",
    "cr9b2_name": "L2_HV",
    "cr9b2_duedate": "22.04.2026 00:00",
    "cr9b2_ilevelnames": "[\"NA00-26-07-510\",\"NA05-26-07-510\"]",
    "cr9b2_parentjiraissue": "PTH-177948",
    "cr9b2_parentbranches": "[\"PTH-06\"]",
    "cr9b2_brvs": "[]",
    "cr9b2_sops": "[]",
    "cr9b2_kw": "17",
    "cr9b2_year": "2.026",
    "cr9b2_yearweek": "2026-17"
  },
  {
    "_id": "88606322-023f-f111-bec6-7ced8d4a3175",
    "cr9b2_jirakey": "PTH-178769",
    "cr9b2_jiraurl": "https://jira.cc.bmwgroup.net/browse/PTH-178769",
    "cr9b2_name": "L4",
    "cr9b2_duedate": "12.05.2026 00:00",
    "cr9b2_ilevelnames": "[\"NA00-26-07-510\",\"NA05-26-07-510\"]",
    "cr9b2_parentjiraissue": "PTH-177948",
    "cr9b2_parentbranches": "[\"PTH-06\"]",
    "cr9b2_brvs": "[]",
    "cr9b2_sops": "[]",
    "cr9b2_kw": "20",
    "cr9b2_year": "2.026",
    "cr9b2_yearweek": "2026-20"
  },
  {
    "_id": "82606322-023f-f111-bec6-7ced8d4a3175",
    "cr9b2_jirakey": "PTH-173060",
    "cr9b2_jiraurl": "https://jira.cc.bmwgroup.net/browse/PTH-173060",
    "cr9b2_name": "L2_HV",
    "cr9b2_duedate": "03.03.2026 00:00",
    "cr9b2_ilevelnames": "[\"NA06-26-07-490\"]",
    "cr9b2_parentjiraissue": "PTH-173058",
    "cr9b2_parentbranches": "[\"PTH-06\"]",
    "cr9b2_brvs": "[]",
    "cr9b2_sops": "[]",
    "cr9b2_kw": "10",
    "cr9b2_year": "2.026",
    "cr9b2_yearweek": "2026-10"
  },
  {
    "_id": "80606322-023f-f111-bec6-7ced8d4a3175",
    "cr9b2_jirakey": "PTH-169789",
    "cr9b2_jiraurl": "https://jira.cc.bmwgroup.net/browse/PTH-169789",
    "cr9b2_name": "L2_HV",
    "cr9b2_duedate": "19.02.2026 00:00",
    "cr9b2_ilevelnames": "[\"G065-26-11-450\",\"G065-27-03-410\",\"G065-27-07-360\",\"G065-27-11-320\",\"G065-28-03-280\",\"G065-28-07-230\",\"NA00-26-07-480\",\"NA00-26-11-450\",\"NA00-27-03-410\",\"NA00-27-07-360\",\"NA00-27-11-320\",\"NA00-28-03-280\",\"NA00-28-11-190\",\"NA00-29-03-150\",\"NA05-26-07-480\",\"NA05-26-11-450\",\"NA05-27-03-410\",\"NA05-27-07-360\",\"NA05-27-11-320\",\"NA05-28-11-190\",\"NA05-29-03-150\",\"NA06-26-07-480\",\"NA06-26-11-450\",\"NA06-27-03-410\",\"NA06-27-07-360\",\"NA06-28-03-280\",\"NA06-28-07-230\",\"RR45-27-07-360\"]",
    "cr9b2_parentjiraissue": "PTH-168711",
    "cr9b2_parentbranches": "[\"PTH-06\"]",
    "cr9b2_brvs": "[]",
    "cr9b2_sops": "[]",
    "cr9b2_kw": "8",
    "cr9b2_year": "2.026",
    "cr9b2_yearweek": "2026-08"
  },
  {
    "_id": "77606322-023f-f111-bec6-7ced8d4a3175",
    "cr9b2_jirakey": "PTH-162029",
    "cr9b2_jiraurl": "https://jira.cc.bmwgroup.net/browse/PTH-162029",
    "cr9b2_name": "L3_HV",
    "cr9b2_duedate": "05.05.2026 00:00",
    "cr9b2_ilevelnames": "[\"G065-26-11-470\",\"G065-27-03-430\",\"G065-27-07-380\",\"G065-27-11-340\",\"G065-28-03-300\",\"G065-28-07-250\",\"G065-28-11-210\",\"NA00-26-11-470\",\"NA00-27-03-430\",\"NA00-27-07-380\",\"NA00-27-11-340\",\"NA00-28-03-300\",\"NA00-28-11-210\",\"NA00-29-03-170\",\"NA05-26-11-470\",\"NA05-27-03-430\",\"NA05-27-07-380\",\"NA05-27-11-340\",\"NA05-28-11-210\",\"NA05-29-03-170\",\"NA06-26-11-470\",\"NA06-27-03-430\",\"NA06-27-07-380\",\"NA06-28-03-300\",\"NA06-28-07-250\",\"RR45-27-07-380\"]",
    "cr9b2_parentjiraissue": "PTH-162026",
    "cr9b2_parentbranches": "[\"PTH-06\"]",
    "cr9b2_brvs": "[]",
    "cr9b2_sops": "[]",
    "cr9b2_kw": "19",
    "cr9b2_year": "2.026",
    "cr9b2_yearweek": "2026-19"
  },
  {
    "_id": "8dc63b21-023f-f111-bec6-7c1e52873f9b",
    "cr9b2_jirakey": "PTH-179192",
    "cr9b2_jiraurl": "https://jira.cc.bmwgroup.net/browse/PTH-179192",
    "cr9b2_name": "FB",
    "cr9b2_duedate": "05.05.2026 00:00",
    "cr9b2_ilevelnames": "[\"NA05-26-11-480\",\"NA06-26-11-480\",\"NA00-26-11-480\",\"G065-26-11-480\",\"G065-27-03-440\"]",
    "cr9b2_parentjiraissue": "PTH-179188",
    "cr9b2_parentbranches": "[\"PTH-06\"]",
    "cr9b2_brvs": "[]",
    "cr9b2_sops": "[]",
    "cr9b2_kw": "19",
    "cr9b2_year": "2.026",
    "cr9b2_yearweek": "2026-19"
  },
  {
    "_id": "71c63b21-023f-f111-bec6-7c1e52873f9b",
    "cr9b2_jirakey": "PTH-178852",
    "cr9b2_jiraurl": "https://jira.cc.bmwgroup.net/browse/PTH-178852",
    "cr9b2_name": "L2",
    "cr9b2_duedate": "19.05.2026 00:00",
    "cr9b2_ilevelnames": "[\"G065-26-11-480\",\"NA00-26-11-480\",\"NA05-26-11-480\",\"NA06-26-11-480\"]",
    "cr9b2_parentjiraissue": "PTH-178850",
    "cr9b2_parentbranches": "[\"PTH-06\"]",
    "cr9b2_brvs": "[]",
    "cr9b2_sops": "[]",
    "cr9b2_kw": "21",
    "cr9b2_year": "2.026",
    "cr9b2_yearweek": "2026-21"
  },
  {
    "_id": "6fc63b21-023f-f111-bec6-7c1e52873f9b",
    "cr9b2_jirakey": "PTH-180545",
    "cr9b2_jiraurl": "https://jira.cc.bmwgroup.net/browse/PTH-180545",
    "cr9b2_name": "FB",
    "cr9b2_duedate": "05.05.2026 00:00",
    "cr9b2_ilevelnames": "[\"G065-26-11-480\",\"G065-27-03-450\",\"G065-27-07-400\",\"G065-27-11-360\",\"G065-28-03-320\",\"G065-28-07-270\",\"G065-28-11-230\",\"NA00-26-11-480\",\"NA00-27-03-450\",\"NA00-27-07-400\",\"NA00-27-11-360\",\"NA00-28-03-320\",\"NA00-28-11-230\",\"NA00-29-03-190\",\"NA05-26-11-480\",\"NA05-27-03-450\",\"NA05-27-07-400\",\"NA05-27-11-360\",\"NA05-28-11-230\",\"NA05-29-03-190\",\"NA06-26-11-480\",\"NA06-27-03-450\",\"NA06-27-07-400\",\"NA06-27-11-360\",\"NA06-28-03-320\",\"NA06-28-07-270\",\"RR45-27-07-400\"]",
    "cr9b2_parentjiraissue": "PTH-180544",
    "cr9b2_parentbranches": "[\"PTH-06\"]",
    "cr9b2_brvs": "[]",
    "cr9b2_sops": "[]",
    "cr9b2_kw": "19",
    "cr9b2_year": "2.026",
    "cr9b2_yearweek": "2026-19"
  },
  {
    "_id": "6cc63b21-023f-f111-bec6-7c1e52873f9b",
    "cr9b2_jirakey": "PTH-178856",
    "cr9b2_jiraurl": "https://jira.cc.bmwgroup.net/browse/PTH-178856",
    "cr9b2_name": "FB",
    "cr9b2_duedate": "05.05.2026 00:00",
    "cr9b2_ilevelnames": "[\"G065-26-11-480\",\"G065-27-03-450\",\"G065-27-07-400\",\"G065-27-11-360\",\"G065-28-03-320\",\"G065-28-07-270\",\"G065-28-11-230\",\"NA00-26-11-480\",\"NA00-27-03-450\",\"NA00-27-07-400\",\"NA00-27-11-360\",\"NA00-28-03-320\",\"NA00-28-11-230\",\"NA00-29-03-190\",\"NA05-26-11-480\",\"NA05-27-03-450\",\"NA05-27-07-400\",\"NA05-27-11-360\",\"NA05-28-11-230\",\"NA05-29-03-190\",\"NA06-26-11-480\",\"NA06-27-03-450\",\"NA06-27-07-400\",\"NA06-27-11-360\",\"NA06-28-03-320\",\"NA06-28-07-270\",\"RR45-27-07-400\"]",
    "cr9b2_parentjiraissue": "PTH-170497",
    "cr9b2_parentbranches": "[\"PTH-06\"]",
    "cr9b2_brvs": "[]",
    "cr9b2_sops": "[]",
    "cr9b2_kw": "19",
    "cr9b2_year": "2.026",
    "cr9b2_yearweek": "2026-19"
  },
  {
    "_id": "66c63b21-023f-f111-bec6-7c1e52873f9b",
    "cr9b2_jirakey": "PTH-176985",
    "cr9b2_jiraurl": "https://jira.cc.bmwgroup.net/browse/PTH-176985",
    "cr9b2_name": "L3_HV",
    "cr9b2_duedate": "14.04.2026 00:00",
    "cr9b2_ilevelnames": "[\"NA05-26-03-540\"]",
    "cr9b2_parentjiraissue": "PTH-176982",
    "cr9b2_parentbranches": "[\"PTH-06\"]",
    "cr9b2_brvs": "[]",
    "cr9b2_sops": "[]",
    "cr9b2_kw": "16",
    "cr9b2_year": "2.026",
    "cr9b2_yearweek": "2026-16"
  },
  {
    "_id": "60c63b21-023f-f111-bec6-7c1e52873f9b",
    "cr9b2_jirakey": "PTH-176986",
    "cr9b2_jiraurl": "https://jira.cc.bmwgroup.net/browse/PTH-176986",
    "cr9b2_name": "FB",
    "cr9b2_duedate": "26.03.2026 00:00",
    "cr9b2_ilevelnames": "[\"NA05-26-03-540\"]",
    "cr9b2_parentjiraissue": "PTH-176982",
    "cr9b2_parentbranches": "[\"PTH-06\"]",
    "cr9b2_brvs": "[]",
    "cr9b2_sops": "[]",
    "cr9b2_kw": "13",
    "cr9b2_year": "2.026",
    "cr9b2_yearweek": "2026-13"
  },
  {
    "_id": "3ec63b21-023f-f111-bec6-7c1e52873f9b",
    "cr9b2_jirakey": "PTH-173071",
    "cr9b2_jiraurl": "https://jira.cc.bmwgroup.net/browse/PTH-173071",
    "cr9b2_name": "FB",
    "cr9b2_duedate": "07.04.2026 00:00",
    "cr9b2_ilevelnames": "[\"NA05-26-11-470\",\"NA06-26-11-470\",\"NA00-26-11-470\",\"G065-26-11-470\",\"G065-27-03-430\",\"NA00-27-03-430\",\"NA05-27-03-430\",\"NA06-27-03-430\",\"G065-27-07-380\",\"NA00-27-07-380\",\"NA05-27-07-380\",\"NA06-27-07-380\",\"RR45-27-07-380\",\"G065-27-11-340\",\"NA00-27-11-340\",\"NA05-27-11-340\",\"G065-28-03-300\",\"NA00-28-03-300\",\"NA06-28-03-300\",\"G065-28-07-250\",\"NA06-28-07-250\",\"G065-28-11-210\",\"NA05-28-11-210\",\"NA00-28-11-210\",\"NA05-29-03-170\",\"NA00-29-03-170\"]",
    "cr9b2_parentjiraissue": "PTH-173067",
    "cr9b2_parentbranches": "[\"PTH-06\"]",
    "cr9b2_brvs": "[]",
    "cr9b2_sops": "[]",
    "cr9b2_kw": "15",
    "cr9b2_year": "2.026",
    "cr9b2_yearweek": "2026-15"
  },
  {
    "_id": "3cc63b21-023f-f111-bec6-7c1e52873f9b",
    "cr9b2_jirakey": "PTH-173059",
    "cr9b2_jiraurl": "https://jira.cc.bmwgroup.net/browse/PTH-173059",
    "cr9b2_name": "L1_HV",
    "cr9b2_duedate": "05.03.2026 00:00",
    "cr9b2_ilevelnames": "[\"NA06-26-07-490\"]",
    "cr9b2_parentjiraissue": "PTH-173058",
    "cr9b2_parentbranches": "[\"PTH-06\"]",
    "cr9b2_brvs": "[]",
    "cr9b2_sops": "[]",
    "cr9b2_kw": "10",
    "cr9b2_year": "2.026",
    "cr9b2_yearweek": "2026-10"
  },
  {
    "_id": "1cc63b21-023f-f111-bec6-7c1e52873f9b",
    "cr9b2_jirakey": "PTH-163911",
    "cr9b2_jiraurl": "https://jira.cc.bmwgroup.net/browse/PTH-163911",
    "cr9b2_name": "L2_HV",
    "cr9b2_duedate": "24.03.2026 00:00",
    "cr9b2_ilevelnames": "[\"G065-26-11-459\",\"G065-27-03-419\",\"G065-27-07-369\"]",
    "cr9b2_parentjiraissue": "PTH-162412",
    "cr9b2_parentbranches": "[\"PTH-06\"]",
    "cr9b2_brvs": "[]",
    "cr9b2_sops": "[]",
    "cr9b2_kw": "13",
    "cr9b2_year": "2.026",
    "cr9b2_yearweek": "2026-13"
  },
  {
    "_id": "25044e20-023f-f111-bec6-7ced8d4a37b0",
    "cr9b2_jirakey": "PTH-180299",
    "cr9b2_jiraurl": "https://jira.cc.bmwgroup.net/browse/PTH-180299",
    "cr9b2_name": "L2_HV",
    "cr9b2_duedate": "05.05.2026 00:00",
    "cr9b2_ilevelnames": "[\"NA05-26-11-470\",\"NA06-26-11-470\",\"NA00-26-11-470\",\"G065-26-11-470\",\"G065-27-03-430\",\"NA00-27-03-430\",\"NA05-27-03-430\",\"NA06-27-03-430\",\"G065-27-07-380\",\"NA00-27-07-380\",\"NA05-27-07-380\",\"NA06-27-07-380\",\"RR45-27-07-380\",\"G065-27-11-340\",\"NA00-27-11-340\",\"NA05-27-11-340\",\"G065-28-03-300\",\"NA00-28-03-300\",\"NA06-28-03-300\",\"G065-28-07-250\",\"NA06-28-07-250\",\"G065-28-11-210\",\"NA05-28-11-210\",\"NA00-28-11-210\",\"NA05-29-03-170\",\"NA00-29-03-170\"]",
    "cr9b2_parentjiraissue": "PTH-173067",
    "cr9b2_parentbranches": "[\"PTH-06\"]",
    "cr9b2_brvs": "[]",
    "cr9b2_sops": "[]",
    "cr9b2_kw": "19",
    "cr9b2_year": "2.026",
    "cr9b2_yearweek": "2026-19"
  },
  {
    "_id": "21044e20-023f-f111-bec6-7ced8d4a37b0",
    "cr9b2_jirakey": "PTH-176983",
    "cr9b2_jiraurl": "https://jira.cc.bmwgroup.net/browse/PTH-176983",
    "cr9b2_name": "L2_HV",
    "cr9b2_duedate": "26.03.2026 00:00",
    "cr9b2_ilevelnames": "[\"NA05-26-03-540\"]",
    "cr9b2_parentjiraissue": "PTH-176982",
    "cr9b2_parentbranches": "[\"PTH-06\"]",
    "cr9b2_brvs": "[]",
    "cr9b2_sops": "[]",
    "cr9b2_kw": "13",
    "cr9b2_year": "2.026",
    "cr9b2_yearweek": "2026-13"
  },
  {
    "_id": "08044e20-023f-f111-bec6-7ced8d4a37b0",
    "cr9b2_jirakey": "PTH-162005",
    "cr9b2_jiraurl": "https://jira.cc.bmwgroup.net/browse/PTH-162005",
    "cr9b2_name": "L2_HV",
    "cr9b2_duedate": "25.02.2026 00:00",
    "cr9b2_ilevelnames": "[\"NA00-26-07-490\",\"NA05-26-07-490\",\"NA06-26-07-490\"]",
    "cr9b2_parentjiraissue": "PTH-162003",
    "cr9b2_parentbranches": "[\"PTH-06\"]",
    "cr9b2_brvs": "[]",
    "cr9b2_sops": "[]",
    "cr9b2_kw": "9",
    "cr9b2_year": "2.026",
    "cr9b2_yearweek": "2026-09"
  },
  {
    "_id": "3bc63b21-023f-f111-bec6-7c1e52873f9b",
    "cr9b2_jirakey": "PTH-171866",
    "cr9b2_jiraurl": "https://jira.cc.bmwgroup.net/browse/PTH-171866",
    "cr9b2_name": "FB",
    "cr9b2_duedate": "07.04.2026 00:00",
    "cr9b2_ilevelnames": "[\"NA00-26-07-510\"]",
    "cr9b2_parentjiraissue": "PTH-171865",
    "cr9b2_parentbranches": "[\"PTH-06\"]",
    "cr9b2_brvs": "[]",
    "cr9b2_sops": "[]",
    "cr9b2_kw": "15",
    "cr9b2_year": "2.026",
    "cr9b2_yearweek": "2026-15"
  },
  {
    "_id": "33c63b21-023f-f111-bec6-7c1e52873f9b",
    "cr9b2_jirakey": "PTH-170031",
    "cr9b2_jiraurl": "https://jira.cc.bmwgroup.net/browse/PTH-170031",
    "cr9b2_name": "L3_HV",
    "cr9b2_duedate": "17.03.2026 00:00",
    "cr9b2_ilevelnames": "[\"NA00-26-07-490\",\"NA05-26-07-490\",\"NA06-26-07-490\"]",
    "cr9b2_parentjiraissue": "PTH-168337",
    "cr9b2_parentbranches": "[\"PTH-06\"]",
    "cr9b2_brvs": "[]",
    "cr9b2_sops": "[]",
    "cr9b2_kw": "12",
    "cr9b2_year": "2.026",
    "cr9b2_yearweek": "2026-12"
  },
  {
    "_id": "29c63b21-023f-f111-bec6-7c1e52873f9b",
    "cr9b2_jirakey": "PTH-169589",
    "cr9b2_jiraurl": "https://jira.cc.bmwgroup.net/browse/PTH-169589",
    "cr9b2_name": "FB",
    "cr9b2_duedate": "24.02.2026 00:00",
    "cr9b2_ilevelnames": "[\"NA05-26-11-470\",\"NA06-26-11-470\",\"NA00-26-11-470\",\"G065-26-11-470\",\"G065-27-03-430\",\"NA00-27-03-430\",\"NA05-27-03-430\",\"NA06-27-03-430\",\"G065-27-07-380\",\"NA00-27-07-380\",\"NA05-27-07-380\",\"NA06-27-07-380\",\"RR45-27-07-380\",\"G065-27-11-340\",\"NA00-27-11-340\",\"NA05-27-11-340\",\"G065-28-03-300\",\"NA00-28-03-300\",\"NA06-28-03-300\",\"G065-28-07-250\",\"NA06-28-07-250\",\"G065-28-11-210\",\"NA05-28-11-210\",\"NA00-28-11-210\",\"NA05-29-03-170\",\"NA00-29-03-170\"]",
    "cr9b2_parentjiraissue": "PTH-169585",
    "cr9b2_parentbranches": "[\"PTH-06\"]",
    "cr9b2_brvs": "[]",
    "cr9b2_sops": "[]",
    "cr9b2_kw": "9",
    "cr9b2_year": "2.026",
    "cr9b2_yearweek": "2026-09"
  },
  {
    "_id": "25c63b21-023f-f111-bec6-7c1e52873f9b",
    "cr9b2_jirakey": "PTH-168054",
    "cr9b2_jiraurl": "https://jira.cc.bmwgroup.net/browse/PTH-168054",
    "cr9b2_name": "L3_HV",
    "cr9b2_duedate": "10.03.2026 00:00",
    "cr9b2_ilevelnames": "[\"NA05-26-03-530\"]",
    "cr9b2_parentjiraissue": "PTH-168041",
    "cr9b2_parentbranches": "[\"PTH-06\"]",
    "cr9b2_brvs": "[]",
    "cr9b2_sops": "[]",
    "cr9b2_kw": "11",
    "cr9b2_year": "2.026",
    "cr9b2_yearweek": "2026-11"
  },
  {
    "_id": "16c63b21-023f-f111-bec6-7c1e52873f9b",
    "cr9b2_jirakey": "PTH-162006",
    "cr9b2_jiraurl": "https://jira.cc.bmwgroup.net/browse/PTH-162006",
    "cr9b2_name": "L3_HV",
    "cr9b2_duedate": "24.03.2026 00:00",
    "cr9b2_ilevelnames": "[\"NA00-26-07-490\",\"NA05-26-07-490\",\"NA06-26-07-490\"]",
    "cr9b2_parentjiraissue": "PTH-162003",
    "cr9b2_parentbranches": "[\"PTH-06\"]",
    "cr9b2_brvs": "[]",
    "cr9b2_sops": "[]",
    "cr9b2_kw": "13",
    "cr9b2_year": "2.026",
    "cr9b2_yearweek": "2026-13"
  }
]